subterran/__init__.py
subterran/acuifero.py
subterran-0.2.0.dist-info/LICENSE
subterran-0.2.0.dist-info/METADATA
subterran-0.2.0.dist-info/WHEEL
subterran-0.2.0.dist-info/top_level.txt
subterran-0.2.0.dist-info/RECORD
