Metadata-Version: 2.1
Name: subterran
Version: 0.2.0
Summary: Calcula el volumen de agua almacenada en un sistema de acuíferos.
Home-page: https://github.com/yourusername/acuiferoec
Author: Santiago Quiñones
Author-email: lsquinones@gmail.com
Classifier: Programming Language :: Python :: 3
Classifier: License :: OSI Approved :: MIT License
Classifier: Operating System :: OS Independent
Requires-Python: >=3.6
License-File: LICENSE
Requires-Dist: numpy ==1.24.1
